simstring/__init__.py
simstring/searcher.py
simstring/database/__init__.py
simstring/database/base.py
simstring/database/dict.py
simstring/database/mongo.py
simstring/feature_extractor/__init__.py
simstring/feature_extractor/base.py
simstring/feature_extractor/character_ngram.py
simstring/feature_extractor/mecab_ngram.py
simstring/feature_extractor/word_ngram.py
simstring/measure/__init__.py
simstring/measure/base.py
simstring/measure/cosine.py
simstring/measure/dice.py
simstring/measure/jaccard.py
simstring_pure-1.0.0.dist-info/METADATA
simstring_pure-1.0.0.dist-info/RECORD
simstring_pure-1.0.0.dist-info/WHEEL
simstring_pure-1.0.0.dist-info/top_level.txt
