Metadata-Version: 2.1
Name: simstring-pure
Version: 1.0.0
Summary: A Python implementation of the SimString, a simple and efficient algorithm for approximate string matching.
Home-page: https://github.com/nullnull/simstring
Author: Katsuma Narisawa
Author-email: katsuma.narisawa@gmail.com
License: UNKNOWN
Platform: UNKNOWN
Classifier: Development Status :: 5 - Production/Stable
Classifier: Programming Language :: Python :: 3
Classifier: Programming Language :: Python :: 3.7
Classifier: License :: OSI Approved :: MIT License
Classifier: Operating System :: OS Independent
